wordfinds/__init__.py
wordfinds/array.py
wordfinds/main.py
wordfinds/raw.py
wordfinds/utils.py
wordfinds/wordbank.py
Wordfinds-0.0.0.dist-info/METADATA
Wordfinds-0.0.0.dist-info/WHEEL
Wordfinds-0.0.0.dist-info/top_level.txt
Wordfinds-0.0.0.dist-info/RECORD
