Metadata-Version: 2.1
Name: Wordfinds
Version: 0.0.0
Summary: Generate and solve wordfinds in python
Home-page: https://github.com/GrandMoff100/WordFinds
License: UNKNOWN
Platform: UNKNOWN
Requires-Dist: english-words
